databricks_ai_bridge/__init__.py
databricks_ai_bridge/genie.py
databricks_ai_bridge/lakebase.py
databricks_ai_bridge/model_serving_obo_credential_strategy.py
databricks_ai_bridge/vector_search_retriever_tool.py
databricks_ai_bridge/test_utils/vector_search.py
databricks_ai_bridge/utils/annotations.py
databricks_ai_bridge/utils/vector_search.py
databricks_ai_bridge-0.11.0.dist-info/METADATA
databricks_ai_bridge-0.11.0.dist-info/WHEEL
databricks_ai_bridge-0.11.0.dist-info/licenses/LICENSE.txt
databricks_ai_bridge-0.11.0.dist-info/licenses/NOTICE.txt
databricks_ai_bridge-0.11.0.dist-info/RECORD
