Metadata-Version: 2.4
Name: databricks-ai-bridge
Version: 0.11.0
Summary: Official Python library for Databricks AI support
Author-email: Databricks <agent-feedback@databricks.com>
License: Databricks License
License-File: LICENSE.txt
License-File: NOTICE.txt
Requires-Python: >=3.10
Requires-Dist: databricks-sdk>=0.49.0
Requires-Dist: databricks-vectorsearch>=0.57
Requires-Dist: mlflow-skinny>=2.19.0
Requires-Dist: pandas
Requires-Dist: pydantic
Requires-Dist: tabulate>=0.9.0
Requires-Dist: tiktoken>=0.8.0
Requires-Dist: typing-extensions
Provides-Extra: dev
Requires-Dist: hatch; extra == 'dev'
Requires-Dist: mlflow; extra == 'dev'
Requires-Dist: pytest; extra == 'dev'
Requires-Dist: pytest-asyncio; extra == 'dev'
Requires-Dist: ruff==0.12.10; extra == 'dev'
Provides-Extra: doc
Requires-Dist: autodoc-pydantic>=2.2.0; extra == 'doc'
Requires-Dist: commonmark>=0.9.1; extra == 'doc'
Requires-Dist: docutils>=0.21.2; extra == 'doc'
Requires-Dist: jinja2>=3.0.0; extra == 'doc'
Requires-Dist: markupsafe>=3.0.2; extra == 'doc'
Requires-Dist: myst-parser>=4.0.0; extra == 'doc'
Requires-Dist: sphinx-autobuild>=2024.10.3; extra == 'doc'
Requires-Dist: sphinx-rtd-theme>=3.0.1; extra == 'doc'
Requires-Dist: sphinx>=8.1.3; extra == 'doc'
Provides-Extra: lint
Requires-Dist: ruff==0.12.10; extra == 'lint'
Provides-Extra: memory
Requires-Dist: psycopg[binary,pool]>=3.1; extra == 'memory'
